realerikrani/pysteptest/__init__.py
realerikrani/pysteptest/marker.py
realerikrani/pysteptest/py.typed
realerikrani_pysteptest-1.0.0.dist-info/LICENSE
realerikrani_pysteptest-1.0.0.dist-info/LICENSE_OF_PYTEST
realerikrani_pysteptest-1.0.0.dist-info/METADATA
realerikrani_pysteptest-1.0.0.dist-info/WHEEL
realerikrani_pysteptest-1.0.0.dist-info/entry_points.txt
realerikrani_pysteptest-1.0.0.dist-info/top_level.txt
realerikrani_pysteptest-1.0.0.dist-info/RECORD
