Metadata-Version: 2.1
Name: realerikrani-pysteptest
Version: 1.0.0
Summary: Pytest marker @pytest.mark.pysteptest for sequential tests in a class
License: Apache-2.0
Project-URL: Repository, https://github.com/realerikrani/pysteptest
Requires-Python: >=3.10
License-File: LICENSE
License-File: LICENSE_OF_PYTEST
Requires-Dist: pytest==8.*
